sbfit/__init__.py
sbfit/image.py
sbfit/model.py
sbfit/observation.py
sbfit/profile.py
sbfit/region.py
sbfit/statistics.py
sbfit/utils.py
sbfit-0.2.0.dist-info/LICENSE
sbfit-0.2.0.dist-info/METADATA
sbfit-0.2.0.dist-info/WHEEL
sbfit-0.2.0.dist-info/top_level.txt
sbfit-0.2.0.dist-info/RECORD
